README.rst
setup.py
PyTrafodion.egg-info/PKG-INFO
PyTrafodion.egg-info/SOURCES.txt
PyTrafodion.egg-info/dependency_links.txt
PyTrafodion.egg-info/requires.txt
PyTrafodion.egg-info/top_level.txt
pdbc/__init__.py
pdbc/trafodion/__init__.py
pdbc/trafodion/connector/__init__.py
pdbc/trafodion/connector/abstracts.py
pdbc/trafodion/connector/authentication.py
pdbc/trafodion/connector/catch23.py
pdbc/trafodion/connector/connection.py
pdbc/trafodion/connector/converters.py
pdbc/trafodion/connector/cursor.py
pdbc/trafodion/connector/errors.py
pdbc/trafodion/connector/network.py
pdbc/trafodion/connector/statement.py
pdbc/trafodion/connector/struct_def.py
pdbc/trafodion/connector/constants/CONNECTION.py
pdbc/trafodion/connector/constants/FIELD_TYPE.py
pdbc/trafodion/connector/constants/STRUCTDEF.py
pdbc/trafodion/connector/constants/TRANSPORT.py
pdbc/trafodion/connector/constants/__init__.py