Metadata-Version: 1.1
Name: PyTrafodion
Version: 0.0.4
Summary: Pure Python Trafodion Driver
Home-page: https://github.com/CoderSong2015/Trafodion-pythondriver
Author: Haolin Song
Author-email: haolin.song@outlook.com
License: UNKNOWN
Keywords: Trafodion
Platform: UNKNOWN
Classifier: Development Status :: 3 - Alpha
Classifier: Programming Language :: Python :: 3.4
Classifier: Programming Language :: Python :: 3.5
Classifier: Programming Language :: Python :: 3.6
Classifier: Programming Language :: Python :: 3.7
Classifier: Programming Language :: Python :: Implementation :: CPython
Classifier: Intended Audience :: Developers
Classifier: License :: OSI Approved :: Apache Software License
Classifier: Topic :: Database
